{
"meta":{"test_sets":[],"test_metrics":[],"learn_metrics":[{"best_value":"Min","name":"Logloss"}],"launch_mode":"Train","parameters":"","iteration_count":100,"learn_sets":["learn"],"name":"experiment"},
"iterations":[
{"learn":[0.42882548],"iteration":0,"passed_time":0.004960764643,"remaining_time":0.4911156997},
{"learn":[0.3160362586],"iteration":1,"passed_time":0.009373636144,"remaining_time":0.459308171},
{"learn":[0.2577889216],"iteration":2,"passed_time":0.01383795249,"remaining_time":0.4474271306},
{"learn":[0.2213322464],"iteration":3,"passed_time":0.01877406303,"remaining_time":0.4505775128},
{"learn":[0.1956669383],"iteration":4,"passed_time":0.02360099891,"remaining_time":0.4484189793},
{"learn":[0.1794520479],"iteration":5,"passed_time":0.02825329491,"remaining_time":0.4426349537},
{"learn":[0.1681027421],"iteration":6,"passed_time":0.03329324665,"remaining_time":0.4423245626},
{"learn":[0.1584412467],"iteration":7,"passed_time":0.03825418167,"remaining_time":0.4399230892},
{"learn":[0.1521088782],"iteration":8,"passed_time":0.04299375251,"remaining_time":0.4347146087},
{"learn":[0.1464509309],"iteration":9,"passed_time":0.04812014598,"remaining_time":0.4330813138},
{"learn":[0.1405651255],"iteration":10,"passed_time":0.0537253092,"remaining_time":0.4346865927},
{"learn":[0.1380260978],"iteration":11,"passed_time":0.05841077927,"remaining_time":0.4283457146},
{"learn":[0.1324882725],"iteration":12,"passed_time":0.063227824,"remaining_time":0.4231400529},
{"learn":[0.1298252096],"iteration":13,"passed_time":0.0676231363,"remaining_time":0.4153992659},
{"learn":[0.1258062742],"iteration":14,"passed_time":0.07200242283,"remaining_time":0.4080137293},
{"learn":[0.1232324676],"iteration":15,"passed_time":0.07624571575,"remaining_time":0.4002900077},
{"learn":[0.1211766557],"iteration":16,"passed_time":0.08077299266,"remaining_time":0.3943622583},
{"learn":[0.1191461465],"iteration":17,"passed_time":0.08516465681,"remaining_time":0.3879723255},
{"learn":[0.116923205],"iteration":18,"passed_time":0.08956140231,"remaining_time":0.3818143993},
{"learn":[0.1149780804],"iteration":19,"passed_time":0.09420707353,"remaining_time":0.3768282941},
{"learn":[0.1128444615],"iteration":20,"passed_time":0.09841995857,"remaining_time":0.3702465108},
{"learn":[0.1105553778],"iteration":21,"passed_time":0.1028280995,"remaining_time":0.3645723528},
{"learn":[0.1094746277],"iteration":22,"passed_time":0.1072152235,"remaining_time":0.3589379222},
{"learn":[0.1086688095],"iteration":23,"passed_time":0.1118662768,"remaining_time":0.3542432097},
{"learn":[0.1059034991],"iteration":24,"passed_time":0.1162572895,"remaining_time":0.3487718684},
{"learn":[0.1045322392],"iteration":25,"passed_time":0.1207668167,"remaining_time":0.3437209399},
{"learn":[0.1030451519],"iteration":26,"passed_time":0.1253640097,"remaining_time":0.3389471374},
{"learn":[0.1016894369],"iteration":27,"passed_time":0.1297318507,"remaining_time":0.3335961875},
{"learn":[0.1001838781],"iteration":28,"passed_time":0.1343064232,"remaining_time":0.328819174},
{"learn":[0.09905278777],"iteration":29,"passed_time":0.1391606801,"remaining_time":0.3247082535},
{"learn":[0.09788040207],"iteration":30,"passed_time":0.1445611754,"remaining_time":0.3217651969},
{"learn":[0.09662082447],"iteration":31,"passed_time":0.1500947188,"remaining_time":0.3189512774},
{"learn":[0.09561033697],"iteration":32,"passed_time":0.1554866168,"remaining_time":0.3156849493},
{"learn":[0.09446417434],"iteration":33,"passed_time":0.1602658963,"remaining_time":0.311104387},
{"learn":[0.09377031189],"iteration":34,"passed_time":0.1646298887,"remaining_time":0.3057412219},
{"learn":[0.09285694838],"iteration":35,"passed_time":0.1691366689,"remaining_time":0.3006874114},
{"learn":[0.0918112011],"iteration":36,"passed_time":0.1739754112,"remaining_time":0.2962284028},
{"learn":[0.09137263009],"iteration":37,"passed_time":0.1783071315,"remaining_time":0.2909221619},
{"learn":[0.09033300954],"iteration":38,"passed_time":0.1827655948,"remaining_time":0.2858641354},
{"learn":[0.0894074589],"iteration":39,"passed_time":0.1874629013,"remaining_time":0.2811943519},
{"learn":[0.08858207489],"iteration":40,"passed_time":0.1917678418,"remaining_time":0.2759586016},
{"learn":[0.08751931536],"iteration":41,"passed_time":0.1960943906,"remaining_time":0.2707970156},
{"learn":[0.08578262391],"iteration":42,"passed_time":0.2005247721,"remaining_time":0.2658119072},
{"learn":[0.08498779065],"iteration":43,"passed_time":0.2050468274,"remaining_time":0.2609686894},
{"learn":[0.08438176676],"iteration":44,"passed_time":0.2094979142,"remaining_time":0.2560530062},
{"learn":[0.0837180654],"iteration":45,"passed_time":0.2137050063,"remaining_time":0.2508710944},
{"learn":[0.08293803909],"iteration":46,"passed_time":0.2182781757,"remaining_time":0.2461434747},
{"learn":[0.08102676487],"iteration":47,"passed_time":0.2229070284,"remaining_time":0.2414826141},
{"learn":[0.08054714726],"iteration":48,"passed_time":0.2270844543,"remaining_time":0.2363532075},
{"learn":[0.07919069439],"iteration":49,"passed_time":0.2317412503,"remaining_time":0.2317412503},
{"learn":[0.07833098743],"iteration":50,"passed_time":0.2363417917,"remaining_time":0.2270734862},
{"learn":[0.07708479911],"iteration":51,"passed_time":0.2408503568,"remaining_time":0.2223234063},
{"learn":[0.07670367344],"iteration":52,"passed_time":0.2451541047,"remaining_time":0.2174008099},
{"learn":[0.07601901352],"iteration":53,"passed_time":0.2499043995,"remaining_time":0.2128815255},
{"learn":[0.07561347213],"iteration":54,"passed_time":0.2546237151,"remaining_time":0.2083284942},
{"learn":[0.07496425439],"iteration":55,"passed_time":0.2592998945,"remaining_time":0.2037356314},
{"learn":[0.07449223094],"iteration":56,"passed_time":0.2638990208,"remaining_time":0.1990817175},
{"learn":[0.07396159318],"iteration":57,"passed_time":0.2682921592,"remaining_time":0.1942805291},
{"learn":[0.07274896507],"iteration":58,"passed_time":0.2727013325,"remaining_time":0.1895043158},
{"learn":[0.0717987417],"iteration":59,"passed_time":0.2770215972,"remaining_time":0.1846810648},
{"learn":[0.07116672689],"iteration":60,"passed_time":0.2812659024,"remaining_time":0.1798257409},
{"learn":[0.06996183388],"iteration":61,"passed_time":0.2857498826,"remaining_time":0.1751370248},
{"learn":[0.06911093565],"iteration":62,"passed_time":0.2902937867,"remaining_time":0.1704900017},
{"learn":[0.06832642],"iteration":63,"passed_time":0.2949628391,"remaining_time":0.165916597},
{"learn":[0.06694505811],"iteration":64,"passed_time":0.2997452256,"remaining_time":0.1614012753},
{"learn":[0.06611222503],"iteration":65,"passed_time":0.304472078,"remaining_time":0.1568492523},
{"learn":[0.0658110453],"iteration":66,"passed_time":0.3089759937,"remaining_time":0.1521822059},
{"learn":[0.06533407653],"iteration":67,"passed_time":0.3133285906,"remaining_time":0.1474487485},
{"learn":[0.06506755552],"iteration":68,"passed_time":0.3179571236,"remaining_time":0.1428503019},
{"learn":[0.06484330397],"iteration":69,"passed_time":0.3222098366,"remaining_time":0.13808993},
{"learn":[0.06438325624],"iteration":70,"passed_time":0.3268321667,"remaining_time":0.1334948286},
{"learn":[0.06386055256],"iteration":71,"passed_time":0.3316844191,"remaining_time":0.1289883852},
{"learn":[0.06329331195],"iteration":72,"passed_time":0.3363992046,"remaining_time":0.1244216236},
{"learn":[0.06286980904],"iteration":73,"passed_time":0.3413107293,"remaining_time":0.119919986},
{"learn":[0.06160569651],"iteration":74,"passed_time":0.3460798962,"remaining_time":0.1153599654},
{"learn":[0.06074247021],"iteration":75,"passed_time":0.3504805404,"remaining_time":0.1106780654},
{"learn":[0.05990402027],"iteration":76,"passed_time":0.3553036368,"remaining_time":0.1061296577},
{"learn":[0.05964839721],"iteration":77,"passed_time":0.359759514,"remaining_time":0.1014706321},
{"learn":[0.05914749357],"iteration":78,"passed_time":0.3642887264,"remaining_time":0.09683624374},
{"learn":[0.0587591178],"iteration":79,"passed_time":0.3686615686,"remaining_time":0.09216539214},
{"learn":[0.05813416655],"iteration":80,"passed_time":0.373823912,"remaining_time":0.08768709046},
{"learn":[0.05756560359],"iteration":81,"passed_time":0.3783659622,"remaining_time":0.08305594292},
{"learn":[0.05706353927],"iteration":82,"passed_time":0.3829063092,"remaining_time":0.07842659345},
{"learn":[0.05671717595],"iteration":83,"passed_time":0.3874840989,"remaining_time":0.07380649502},
{"learn":[0.05641518789],"iteration":84,"passed_time":0.391806759,"remaining_time":0.06914236923},
{"learn":[0.0560097833],"iteration":85,"passed_time":0.3962276985,"remaining_time":0.06450218348},
{"learn":[0.05575720702],"iteration":86,"passed_time":0.4008685991,"remaining_time":0.05989990561},
{"learn":[0.05514162826],"iteration":87,"passed_time":0.4055756463,"remaining_time":0.05530576996},
{"learn":[0.05471468477],"iteration":88,"passed_time":0.4101533568,"remaining_time":0.05069311151},
{"learn":[0.05420196293],"iteration":89,"passed_time":0.4145753587,"remaining_time":0.04606392874},
{"learn":[0.05402924554],"iteration":90,"passed_time":0.4195324351,"remaining_time":0.04149221885},
{"learn":[0.05359093154],"iteration":91,"passed_time":0.4243882554,"remaining_time":0.03690332656},
{"learn":[0.05276237225],"iteration":92,"passed_time":0.4297448027,"remaining_time":0.032346383},
{"learn":[0.05223728088],"iteration":93,"passed_time":0.4348273392,"remaining_time":0.02775493654},
{"learn":[0.05192791836],"iteration":94,"passed_time":0.4393182747,"remaining_time":0.02312201446},
{"learn":[0.05110297375],"iteration":95,"passed_time":0.4439187753,"remaining_time":0.01849661564},
{"learn":[0.05062760921],"iteration":96,"passed_time":0.4481343163,"remaining_time":0.01385982422},
{"learn":[0.05007945763],"iteration":97,"passed_time":0.4526401153,"remaining_time":0.009237553373},
{"learn":[0.04925435964],"iteration":98,"passed_time":0.4572445143,"remaining_time":0.004618631458},
{"learn":[0.04886676733],"iteration":99,"passed_time":0.4624093245,"remaining_time":0}
]}