{
  "CatBoost": {
    "accuracy": 0.7374,
    "f1_weighted": 0.7515,
    "roc_auc": 0.8455,
    "pr_auc": 0.6683,
    "brier": 0.1635,
    "time_s": 4.1
  },
  "LightGBM": {
    "accuracy": 0.7573,
    "f1_weighted": 0.7687,
    "roc_auc": 0.8405,
    "pr_auc": 0.6441,
    "brier": 0.1587,
    "time_s": 1.2
  },
  "XGBoost": {
    "accuracy": 0.7857,
    "f1_weighted": 0.7582,
    "roc_auc": 0.8328,
    "pr_auc": 0.6281,
    "brier": 0.1447,
    "time_s": 0.4
  },
  "TabM": {
    "accuracy": 0.7573,
    "f1_weighted": 0.7583,
    "roc_auc": 0.8026,
    "pr_auc": 0.571,
    "brier": 0.1661,
    "time_s": 1.5
  },
  "FLAML": {
    "accuracy": 0.7963,
    "f1_weighted": 0.7873,
    "roc_auc": 0.8451,
    "pr_auc": 0.6604,
    "brier": 0.1356,
    "time_s": 121.0
  }
}